pydantic_tes-0.2.0.dist-info/licenses/LICENSE
pydantictes/__init__.py
pydantictes/api.py
pydantictes/funnelfixture.py
pydantictes/funnelwrapper.py
pydantictes/models.py
pydantictes/py.typed
test/__init__.py
test/conftest.py
test/test_funnel.py
pydantic_tes-0.2.0.dist-info/METADATA
pydantic_tes-0.2.0.dist-info/WHEEL
pydantic_tes-0.2.0.dist-info/top_level.txt
pydantic_tes-0.2.0.dist-info/RECORD
