Metadata-Version: 2.4
Name: pydantic-tes
Version: 0.2.0
Summary: Pydantic Models for the GA4GH Task Execution Service
Author: John Chilton
Author-email: jmchilton@gmail.com
License: MIT
Project-URL: Bug Tracker, https://github.com/jmchilton/pydantic-tes/issues
Project-URL: Source Code, https://github.com/jmchilton/pydantic-tes/issues
Classifier: Development Status :: 5 - Production/Stable
Classifier: Intended Audience :: Developers
Classifier: License :: OSI Approved :: MIT License
Classifier: Operating System :: OS Independent
Classifier: Programming Language :: Python :: 3
Classifier: Programming Language :: Python :: 3.6
Classifier: Programming Language :: Python :: 3.7
Classifier: Programming Language :: Python :: 3.8
Classifier: Programming Language :: Python :: 3.9
Classifier: Programming Language :: Python :: 3.10
Requires-Python: >=3.6
License-File: LICENSE
Requires-Dist: pydantic
Requires-Dist: requests
Requires-Dist: typing-extensions
Provides-Extra: testing
Requires-Dist: pytest; extra == "testing"
Dynamic: license-file
